Metadata-Version: 1.0
Name: bigbharath-probability
Version: 1.0
Summary: Gaussian and Binomial distributions
Home-page: UNKNOWN
Author: Bharath C S
Author-email: bharath.sdupuc@gmail.com
License: UNKNOWN
Platform: UNKNOWN
